ass_autoclip/FrameSlider.qml
ass_autoclip/Hamburger.qml
ass_autoclip/ValueSlider.qml
ass_autoclip/__init__.py
ass_autoclip/__main__.py
ass_autoclip/autoclip.py
ass_autoclip/autoclip.qml
ass_autoclip/base.py
ass_autoclip/magic.py
ass_autoclip/assets/LICENSE.OFL.txt
ass_autoclip/assets/NotoSansDisplay-Medium.ttf
ass_autoclip-2.1.1.dist-info/METADATA
ass_autoclip-2.1.1.dist-info/WHEEL
ass_autoclip-2.1.1.dist-info/licenses/LICENSE
ass_autoclip-2.1.1.dist-info/RECORD
