Metadata-Version: 2.4
Name: ass-autoclip
Version: 2.1.1
Summary: 𝓪𝓾𝓽𝓸𝓶𝓪𝓰𝓲𝓬𝓪𝓵𝓵𝔂
Project-URL: Documentation, https://github.com/Zahuczky/Zahuczkys-Aegisub-Scripts
Project-URL: Issues, https://github.com/Zahuczky/Zahuczkys-Aegisub-Scripts/issues
Project-URL: Source, https://github.com/Zahuczky/Zahuczkys-Aegisub-Scripts
Author-email: Zahuczky <zahuczky@proton.me>, Akatsumekusa <Akatsumekusa@protonmail.com>
License-Expression: BSD-3-Clause
License-File: LICENSE
Keywords: VapourSynth
Classifier: License :: OSI Approved :: BSD License
Classifier: Programming Language :: Python
Classifier: Programming Language :: Python :: 3.8
Classifier: Programming Language :: Python :: 3.9
Classifier: Programming Language :: Python :: 3.10
Classifier: Programming Language :: Python :: 3.11
Classifier: Topic :: Multimedia :: Video
Requires-Python: >=3.8
Requires-Dist: numpy
Requires-Dist: pyside6
Requires-Dist: scikit-image
